Metadata-Version: 1.1
Name: pyJect
Version: 2.2.5
Summary: a command line tool to make and orginize projects
Home-page: UNKNOWN
Author: Kyle Roux
Author-email: jstacoder@gmail.com
License: UNKNOWN
Platform: UNKNOWN
Requires: versionup
